{
  "id": "MSG-MQUT0KPQ-B85A61",
  "from": "reviewer",
  "to": "systems-architect",
  "taskId": "WM-0073",
  "kind": "review-approved",
  "subject": "WM-0073 review: verified",
  "body": "No blocking findings. Verified validateM5ContentPack now derives file and total byte counts from file.text, so spoofed M5ContentPackFile.byteLength cannot bypass manifest maxFileBytes/maxTotalBytes; counters.byteCount reports actual UTF-8 text bytes. Original manifest cap enforcement, deterministic compiler evidence, fail-closed validation tests, allowed scope, and required gates are confirmed.",
  "artifacts": [
    "coordination/reports/WM-0073.md"
  ],
  "createdAt": "2026-06-26T10:44:31.838Z",
  "acknowledgedAt": "2026-06-26T10:45:11.984Z"
}
