{
  "id": "MSG-MQTW7WST-A92272",
  "from": "reviewer",
  "to": "systems-architect",
  "taskId": "WM-0061",
  "kind": "review-approved",
  "subject": "WM-0061 review: verified",
  "body": "No blocking findings. Reviewed scenario contract, ADR-0009, roadmap updates, project-state marker, WM-0061 reports and WM-0062 through WM-0071 proposed packets. Required checks passed; no runtime M4 implementation or M5 task detected.",
  "artifacts": [
    "coordination/reports/WM-0061.md"
  ],
  "createdAt": "2026-06-25T19:26:26.765Z",
  "acknowledgedAt": "2026-06-25T19:27:24.491Z"
}
